{
    "capabilityDescription": "",
    "capability": {
        "appActivity": "com.emanuelef.remote_capture.activities.Activity712",
        "appium": "http://127.0.0.1:4723/wd/hub",
        "noReset": "true",
        "dontStopAppOnReset": "false",
        "appPackage": "cn.jiangemian.client",
        "fullReset": "false"
    },
    "max": {
        "startAfterNSecondsofsleep": 6908,
        "wakeupAfterNSecondsofsleep": 3501,
        "takeScreenShot": false,
        "savePageSource": false,
        "saveCurrentEventPoint": false
    },
    "activities": [
        {
            "prob": 1,
            "activity": "com.tencent.tim.SplashActivity",
            "actions": [
                {
                    "xpath": "//*[@resource-id='com.emanuelef.remote_capture:id/app_filter_switch']",
                    "action": "ZOOM_OUT",
                    "throttle": 619
                }
            ]
        },
        {
            "prob": 1,
            "activity": "com.shibaqiang.forum.Activity221",
            "actions": [
                {
                    "xpath": "//*[@class='android.widget.EditText' and @text='搜索应用']",
                    "action": "ZOOM_OUT",
                    "throttle": 2458
                },
                {
                    "xpath": "//*[@resource-id='com.xxx.go:id/bbb']",
                    "action": "LONG_CLICK",
                    "throttle": 1771
                },
                {
                    "xpath": "//*[@class='android.widget.EditText' and @text='搜索应用']",
                    "action": "CLICK",
                    "throttle": 2144
                },
                {
                    "xpath": "//*[@resource-id='com.xxx.go:id/element637']",
                    "action": "CLICK",
                    "throttle": 2249
                }
            ]
        },
        {
            "prob": 1,
            "activity": "com.emanuelef.remote_capture.activities.Activity304",
            "actions": [
                {
                    "xpath": "//*[@class='android.widget.EditText' and @text='搜索应用']",
                    "action": "INPUTTEXT",
                    "throttle": 1454,
                    "text": "设置"
                },
                {
                    "xpath": "//*[@class='android.widget.TextView' and @text='com.example.b12']",
                    "action": "LONG_CLICK",
                    "throttle": 1527
                },
                {
                    "xpath": "//*[@class='android.widget.TextView' and @text='com.example.b12']",
                    "action": "ZOOM_OUT",
                    "throttle": 1171
                },
                {
                    "xpath": "//*[@resource-id='com.emanuelef.remote_capture:id/app_filter_switch']",
                    "action": "SWIPE",
                    "throttle": 631
                },
                {
                    "xpath": "//*[@class='android.widget.TextView' and @text='com.example.b12']",
                    "action": "CLICK",
                    "throttle": 1127
                }
            ]
        },
        {
            "prob": 1,
            "activity": "com.shibaqiang.forum.Activity33",
            "actions": [
                {
                    "xpath": "//*[@class='android.widget.EditText' and @text='搜索应用']",
                    "action": "ZOOM_IN",
                    "throttle": 2499
                },
                {
                    "xpath": "//*[@resource-id='com.emanuelef.remote_capture:id/app_filter_switch']",
                    "action": "ZOOM_IN",
                    "throttle": 1936
                },
                {
                    "xpath": "//*[@class='android.widget.TextView' and @text='com.example.b12']",
                    "action": "LONG_CLICK",
                    "throttle": 2747
                }
            ]
        },
        {
            "prob": 1,
            "activity": "com.shibaqiang.forum.Activity535",
            "actions": [
                {
                    "xpath": "//*[@resource-id='com.xxx.go:id/element663']",
                    "action": "LONG_CLICK",
                    "throttle": 1782
                },
                {
                    "xpath": "//*[@resource-id='com.xxx.go:id/bbb']",
                    "action": "DRAG",
                    "throttle": 2750
                },
                {
                    "xpath": "//*[@resource-id='com.xxx.go:id/element493']",
                    "action": "CLICK",
                    "throttle": 2461
                },
                {
                    "xpath": "//*[@resource-id='com.xxx.go:id/bbb']",
                    "action": "SCROLL",
                    "throttle": 2788
                },
                {
                    "xpath": "//*[@resource-id='com.xxx.go:id/element471']",
                    "action": "ZOOM_OUT",
                    "throttle": 2349
                }
            ]
        },
        {
            "prob": 1,
            "activity": "com.emanuelef.remote_capture.activities.Activity36",
            "actions": [
                {
                    "xpath": "//*[@class='android.widget.TextView' and @text='com.example.b12']",
                    "action": "INPUTTEXT",
                    "throttle": 2010,
                    "text": "备份"
                },
                {
                    "xpath": "//*[@class='android.widget.EditText' and @text='搜索应用']",
                    "action": "DRAG",
                    "throttle": 1857
                },
                {
                    "xpath": "//*[@resource-id='com.emanuelef.remote_capture:id/app_filter_switch']",
                    "action": "ZOOM_OUT",
                    "throttle": 632
                },
                {
                    "xpath": "//*[@resource-id='com.xxx.go:id/element151']",
                    "action": "DRAG",
                    "throttle": 1362
                },
                {
                    "xpath": "//*[@resource-id='com.emanuelef.remote_capture:id/app_filter_switch']",
                    "action": "SCROLL",
                    "throttle": 738
                }
            ]
        },
        {
            "prob": 1,
            "activity": "com.tencent.tim.SplashActivity",
            "actions": [
                {
                    "xpath": "//*[@class='android.widget.EditText' and @text='搜索应用']",
                    "action": "ZOOM_OUT",
                    "throttle": 2753
                },
                {
                    "xpath": "//*[@resource-id='com.emanuelef.remote_capture:id/app_filter_switch']",
                    "action": "CLICK",
                    "throttle": 2179
                }
            ]
        },
        {
            "prob": 1,
            "activity": "com.shibaqiang.forum.Activity270",
            "actions": [
                {
                    "xpath": "//*[@class='android.widget.TextView' and @text='com.example.b12']",
                    "action": "DRAG",
                    "throttle": 718
                },
                {
                    "xpath": "//*[@resource-id='com.xxx.go:id/bbb']",
                    "action": "SCROLL",
                    "throttle": 1751
                },
                {
                    "xpath": "//*[@resource-id='com.emanuelef.remote_capture:id/app_filter_switch']",
                    "action": "DOUBLE_CLICK",
                    "throttle": 815
                },
                {
                    "xpath": "//*[@resource-id='com.xxx.go:id/element451']",
                    "action": "SWIPE",
                    "throttle": 660
                },
                {
                    "xpath": "//*[@resource-id='com.emanuelef.remote_capture:id/app_filter_switch']",
                    "action": "ZOOM_OUT",
                    "throttle": 2188
                }
            ]
        }
    ]
}