{
    "capabilityDescription": "",
    "capability": {
        "appActivity": "com.tencent.tim.SplashActivity",
        "appium": "http://127.0.0.1:4723/wd/hub",
        "noReset": "true",
        "dontStopAppOnReset": "false",
        "appPackage": "cn.jiangemian.client",
        "fullReset": "false"
    },
    "max": {
        "startAfterNSecondsofsleep": 8579,
        "wakeupAfterNSecondsofsleep": 3531,
        "takeScreenShot": false,
        "savePageSource": false,
        "saveCurrentEventPoint": false
    },
    "activities": [
        {
            "prob": 1,
            "activity": "com.lovewith.lovewith.DetailActivity",
            "actions": [
                {
                    "xpath": "//*[@class='android.widget.TextView' and @text='com.example.b12']",
                    "action": "SWIPE",
                    "throttle": 2104
                },
                {
                    "xpath": "//*[@resource-id='com.xxx.go:id/element147']",
                    "action": "ZOOM_IN",
                    "throttle": 2060
                }
            ]
        },
        {
            "prob": 1,
            "activity": "com.emanuelef.remote_capture.activities.Activity265",
            "actions": [
                {
                    "xpath": "//*[@class='android.widget.TextView' and @text='com.example.b12']",
                    "action": "CLICK",
                    "throttle": 2686
                },
                {
                    "xpath": "//*[@resource-id='com.xxx.go:id/bbb']",
                    "action": "SCROLL",
                    "throttle": 1076
                }
            ]
        },
        {
            "prob": 1,
            "activity": "com.emanuelef.remote_capture.activities.Activity805",
            "actions": [
                {
                    "xpath": "//*[@class='android.widget.TextView' and @text='com.example.b12']",
                    "action": "LONG_CLICK",
                    "throttle": 2466
                },
                {
                    "xpath": "//*[@resource-id='com.xxx.go:id/element911']",
                    "action": "CLICK",
                    "throttle": 2326
                },
                {
                    "xpath": "//*[@class='android.widget.EditText' and @text='搜索应用']",
                    "action": "LONG_CLICK",
                    "throttle": 2351
                },
                {
                    "xpath": "//*[@resource-id='com.xxx.go:id/bbb']",
                    "action": "ZOOM_OUT",
                    "throttle": 1455
                },
                {
                    "xpath": "//*[@class='android.widget.TextView' and @text='com.example.b12']",
                    "action": "CLICK",
                    "throttle": 2178
                }
            ]
        },
        {
            "prob": 1,
            "activity": "com.segmentfault.app.SettingsActivity",
            "actions": [
                {
                    "xpath": "//*[@resource-id='com.xxx.go:id/bbb']",
                    "action": "SWIPE",
                    "throttle": 2225
                },
                {
                    "xpath": "//*[@class='android.widget.TextView' and @text='com.example.b12']",
                    "action": "DOUBLE_CLICK",
                    "throttle": 645
                }
            ]
        },
        {
            "prob": 1,
            "activity": "com.tencent.tim.SplashActivity",
            "actions": [
                {
                    "xpath": "//*[@resource-id='com.emanuelef.remote_capture:id/app_filter_switch']",
                    "action": "ZOOM_IN",
                    "throttle": 1764
                },
                {
                    "xpath": "//*[@class='android.widget.TextView' and @text='com.example.b12']",
                    "action": "ZOOM_OUT",
                    "throttle": 1015
                },
                {
                    "xpath": "//*[@resource-id='com.emanuelef.remote_capture:id/app_filter_switch']",
                    "action": "DRAG",
                    "throttle": 2936
                }
            ]
        },
        {
            "prob": 1,
            "activity": "com.segmentfault.app.SettingsActivity",
            "actions": [
                {
                    "xpath": "//*[@resource-id='com.xxx.go:id/element40']",
                    "action": "DOUBLE_CLICK",
                    "throttle": 2760
                },
                {
                    "xpath": "//*[@resource-id='com.xxx.go:id/element156']",
                    "action": "ZOOM_IN",
                    "throttle": 1271
                },
                {
                    "xpath": "//*[@class='android.widget.TextView' and @text='com.example.b12']",
                    "action": "ZOOM_OUT",
                    "throttle": 860
                },
                {
                    "xpath": "//*[@class='android.widget.EditText' and @text='搜索应用']",
                    "action": "DOUBLE_CLICK",
                    "throttle": 1805
                },
                {
                    "xpath": "//*[@resource-id='com.xxx.go:id/bbb']",
                    "action": "SWIPE",
                    "throttle": 2419
                }
            ]
        },
        {
            "prob": 1,
            "activity": "com.shibaqiang.forum.Activity257",
            "actions": [
                {
                    "xpath": "//*[@class='android.widget.TextView' and @text='com.example.b12']",
                    "action": "CLICK",
                    "throttle": 572
                }
            ]
        },
        {
            "prob": 1,
            "activity": "com.emanuelef.remote_capture.activities.Activity605",
            "actions": [
                {
                    "xpath": "//*[@resource-id='com.xxx.go:id/bbb']",
                    "action": "CLICK",
                    "throttle": 1169
                },
                {
                    "xpath": "//*[@resource-id='com.xxx.go:id/element391']",
                    "action": "ZOOM_OUT",
                    "throttle": 2475
                },
                {
                    "xpath": "//*[@resource-id='com.emanuelef.remote_capture:id/app_filter_switch']",
                    "action": "ZOOM_OUT",
                    "throttle": 2635
                },
                {
                    "xpath": "//*[@resource-id='com.xxx.go:id/element11']",
                    "action": "ZOOM_IN",
                    "throttle": 1797
                },
                {
                    "xpath": "//*[@resource-id='com.xxx.go:id/bbb']",
                    "action": "SWIPE",
                    "throttle": 1178
                }
            ]
        },
        {
            "prob": 1,
            "activity": "com.tencent.tim.SplashActivity",
            "actions": [
                {
                    "xpath": "//*[@resource-id='com.emanuelef.remote_capture:id/app_filter_switch']",
                    "action": "SCROLL",
                    "throttle": 1699
                },
                {
                    "xpath": "//*[@class='android.widget.EditText' and @text='搜索应用']",
                    "action": "ZOOM_IN",
                    "throttle": 1047
                },
                {
                    "xpath": "//*[@class='android.widget.TextView' and @text='com.example.b12']",
                    "action": "SWIPE",
                    "throttle": 2412
                }
            ]
        },
        {
            "prob": 1,
            "activity": "com.segmentfault.app.SettingsActivity",
            "actions": [
                {
                    "xpath": "//*[@resource-id='com.xxx.go:id/bbb']",
                    "action": "ZOOM_IN",
                    "throttle": 2082
                },
                {
                    "xpath": "//*[@resource-id='com.xxx.go:id/bbb']",
                    "action": "DRAG",
                    "throttle": 1168
                },
                {
                    "xpath": "//*[@resource-id='com.xxx.go:id/element831']",
                    "action": "DRAG",
                    "throttle": 2156
                },
                {
                    "xpath": "//*[@resource-id='com.emanuelef.remote_capture:id/app_filter_switch']",
                    "action": "LONG_CLICK",
                    "throttle": 1092
                }
            ]
        },
        {
            "prob": 1,
            "activity": "com.emanuelef.remote_capture.activities.Activity235",
            "actions": [
                {
                    "xpath": "//*[@resource-id='com.xxx.go:id/element930']",
                    "action": "DRAG",
                    "throttle": 1440
                },
                {
                    "xpath": "//*[@resource-id='com.xxx.go:id/element277']",
                    "action": "DRAG",
                    "throttle": 2469
                },
                {
                    "xpath": "//*[@resource-id='com.xxx.go:id/bbb']",
                    "action": "CLICK",
                    "throttle": 2542
                }
            ]
        },
        {
            "prob": 1,
            "activity": "com.tencent.tim.SplashActivity",
            "actions": [
                {
                    "xpath": "//*[@class='android.widget.TextView' and @text='com.example.b12']",
                    "action": "SWIPE",
                    "throttle": 1202
                }
            ]
        },
        {
            "prob": 1,
            "activity": "com.emanuelef.remote_capture.activities.Activity265",
            "actions": [
                {
                    "xpath": "//*[@resource-id='com.emanuelef.remote_capture:id/app_filter_switch']",
                    "action": "ZOOM_OUT",
                    "throttle": 2086
                },
                {
                    "xpath": "//*[@class='android.widget.EditText' and @text='搜索应用']",
                    "action": "DRAG",
                    "throttle": 2654
                },
                {
                    "xpath": "//*[@resource-id='com.emanuelef.remote_capture:id/app_filter_switch']",
                    "action": "LONG_CLICK",
                    "throttle": 2128
                },
                {
                    "xpath": "//*[@resource-id='com.xxx.go:id/bbb']",
                    "action": "INPUTTEXT",
                    "throttle": 919,
                    "text": "暂停播放"
                },
                {
                    "xpath": "//*[@resource-id='com.xxx.go:id/bbb']",
                    "action": "SCROLL",
                    "throttle": 693
                }
            ]
        }
    ]
}